MANIFEST.in
README.rst
setup.cfg
setup.py
flask_consulate/__init__.py
flask_consulate/consul.py
flask_consulate/decorators.py
flask_consulate/exceptions.py
flask_consulate/service.py
flask_consulate.egg-info/PKG-INFO
flask_consulate.egg-info/SOURCES.txt
flask_consulate.egg-info/dependency_links.txt
flask_consulate.egg-info/not-zip-safe
flask_consulate.egg-info/requires.txt
flask_consulate.egg-info/top_level.txt